funciones_prueba/__init__.py
funciones_prueba/funcionesmultivariable.py
funciones_prueba/funcionesunivariable.py
metodos_multivariable/__init__.py
metodos_multivariable/caminata_aleatoria.py
metodos_multivariable/met_cauchy.py
metodos_multivariable/met_fletcher_reeves.py
metodos_multivariable/met_hooke_jeeves.py
metodos_multivariable/met_newton.py
metodos_multivariable/nelder_mead_simplex.py
metodos_univariable/__init__.py
metodos_univariable/bisection.py
metodos_univariable/fibonacci.py
metodos_univariable/golden_section.py
metodos_univariable/interval_halving.py
metodos_univariable/newton_raphson.py
metodos_univariable/secante.py
Lib_optimizacionbyzain-0.1.1.dist-info/LICENSE
Lib_optimizacionbyzain-0.1.1.dist-info/METADATA
Lib_optimizacionbyzain-0.1.1.dist-info/WHEEL
Lib_optimizacionbyzain-0.1.1.dist-info/top_level.txt
Lib_optimizacionbyzain-0.1.1.dist-info/RECORD
