Metadata-Version: 2.1
Name: Lib_optimizacionbyzain
Version: 0.1.1
Summary: Una gran variedad de metodos de optimizacion
Author-email: Zain <azi3lmtz@gmail.com>
Project-URL: Homepage, https://github.com/zamm079/Lib-optimizacion-byzain
Project-URL: Issues, https://github.com/zamm079/Lib-optimizacion-byzain/issues
Classifier: Programming Language :: Python :: 3
Classifier: License :: OSI Approved :: MIT License
Classifier: Operating System :: OS Independent
Requires-Python: >=3.8
License-File: LICENSE
